[{"agendaPoint": "3Spreekrecht burgers", "time": "00:00:00"}, {"agendaPoint": "3.aMevrouw F. van Moorsel spreekt in over aanvraag Cannabis Boutique i.r.t. agendapunt 4 (APV)", "time": "00:14:43"}, {"agendaPoint": "Bestuur", "time": "00:00:00"}, {"agendaPoint": "4Algemene Plaatselijke Verordening 2023 (met presentatie)", "time": "00:29:32"}, {"agendaPoint": "Middelen", "time": "00:00:00"}, {"agendaPoint": "5Treasury 2023", "time": "00:00:00"}, {"agendaPoint": "6Zienswijze DG&J, P&C Cyclus", "time": "00:00:00"}, {"agendaPoint": "7Zienswijze 2e wijziging GR SVHW", "time": "00:00:22"}, {"agendaPoint": "8Sluiting", "time": "00:00:21"}, {"agendaPoint": "1Opening en vaststelling agenda"}, {"agendaPoint": "2Mededelingen"}]