[{"agendaPoint": "1Opening en vaststelling agenda", "time": "00:04:48"}, {"agendaPoint": "2Mededelingen", "time": "00:03:44"}, {"agendaPoint": "3Spreekrecht burgers", "time": "00:00:18"}, {"agendaPoint": "9Wijzigingen Gemeenschappelijke Regelingen", "time": "00:00:09"}, {"agendaPoint": "9.aDienst Gezondheid & Jeugd ZHZ", "time": "00:00:15"}, {"agendaPoint": "9.bVeiligheidsregio ZHZ", "time": "00:00:37"}, {"agendaPoint": "9.cSchadevergoedingsschap HSL, A16 en A4", "time": "00:00:31"}, {"agendaPoint": "4Bestemmingsplan Langeweg 3 Goudswaard/Oud-Piershilseweg 4a Piershil", "time": "00:10:20"}, {"agendaPoint": "5Bestemmingsplan De Boomgaard te Mijnsheerenland", "time": "00:35:00"}, {"agendaPoint": "6Bestemmingsplan Bij de Watertoren te 's-Gravendeel", "time": "00:03:05"}, {"agendaPoint": "7Visie op flexwonen Hoeksche Waard", "time": "00:39:51"}, {"agendaPoint": "8Duurzaamheidslening gemeente Hoeksche Waard", "time": "00:31:14"}, {"agendaPoint": "10Besturenfusie Openbaar Onderwijs Hoeksche Waard", "time": "00:14:11"}, {"agendaPoint": "11Jaarstukken 2018 voormalige gemeenten en Gemeenschappelijke Regelingen", "time": "00:13:45"}, {"agendaPoint": "12Procedureverordening voor advisering tegemoetkoming in planschade 2019", "time": "00:01:00"}, {"agendaPoint": "13Aansluitverordening riolering 2019", "time": "00:00:14"}, {"agendaPoint": "14Verordening ambtelijke bijstand en fractieondersteuning", "time": "00:00:11"}, {"agendaPoint": "15Verordening rechtspositie raads- en commissieleden", "time": "00:00:40"}, {"agendaPoint": "16Communicatieplan raadscommunicatie op hoofdlijnen", "time": "00:08:59"}, {"agendaPoint": "17Aanbesteding accountant", "time": "00:07:01"}, {"agendaPoint": "18Sluiting Openbaar gedeelte", "time": "00:00:16"}, {"agendaPoint": "1Opening Besloten gedeelte", "time": "00:00:01"}, {"agendaPoint": "2Meerjaren Perspectief Grondexploitatie", "time": "00:00:01"}, {"agendaPoint": "3Sluiting Besloten gedeelte", "time": "00:00:01"}]