[{"agendaPoint": "0.Besluitenlijst en notulen", "time": "00:00:01"}, {"agendaPoint": "1.Opening en vaststelling van de agenda", "time": "00:00:35"}, {"agendaPoint": "2.Spreekrecht voor hen die zich hebben aangemeld", "time": "00:00:04"}, {"agendaPoint": "3.Vaststellen besluitenlijst commissie Samen leven van 31 augustus 2017", "time": "00:02:38"}, {"agendaPoint": "4.Concept Beleidsplan 2018-2022 Veiligheidsregio Rotterdam-Rijnmond", "time": "00:42:27"}, {"agendaPoint": "5.Verordening maatschappelijke Ondersteuning Ridderkerk 2018", "time": "00:31:34"}, {"agendaPoint": "6.Wensen en bedenkingen op voorgenomen collegebesluit (principebesluit) tot behouden van aandelen Eneco Groep N.V.", "time": "00:29:16"}, {"agendaPoint": "7.Afvalinzameling bij Ide\u00eble instellingen", "time": "00:21:08"}, {"agendaPoint": "8.Mededelingen gemeenschappelijke regelingen", "time": "00:00:12"}, {"agendaPoint": "9.Mededelingen college ontwikkelingen drie decentralisaties", "time": "00:00:06"}, {"agendaPoint": "10.Mededelingen college", "time": "00:00:03"}, {"agendaPoint": "11.Rondvraag leden", "time": "00:00:53"}, {"agendaPoint": "12.Ter kennisneming: raadsinformatiebrieven", "time": "00:01:00"}, {"agendaPoint": "13.Ter kennisneming: overige stukken", "time": "00:00:24"}]