[{"agendaPoint": "0.Besluitenlijst en notulen", "time": "00:00:01"}, {"agendaPoint": "1.Opening en vaststelling van de agenda", "time": "00:00:49"}, {"agendaPoint": "2.Spreekrecht voor hen die zich hebben aangemeld", "time": "00:00:04"}, {"agendaPoint": "3.Vaststellen besluitenlijst commissie Samen leven van 11 januari 2018", "time": "00:01:41"}, {"agendaPoint": "4.Rapport rekenkamercommissie Kaderstellende rol van de gemeenteraad", "time": "00:39:27"}, {"agendaPoint": "5.Algemene Plaatselijke Verordening Ridderkerk 2018", "time": "00:23:05"}, {"agendaPoint": "6.Aanvraag suppletie uitkering bommenregeling Lancaster", "time": "00:06:38"}, {"agendaPoint": "7.Intrekking Brandbeveiligingsverordening", "time": "00:01:42"}, {"agendaPoint": "8.Kadernotitie subsidiebeleid 2018 - 2022 Ridderkerk", "time": "00:38:12"}, {"agendaPoint": "9.Verordening Leerlingenvervoer Ridderkerk 2018", "time": "00:04:26"}, {"agendaPoint": "10.Overleg samenstelling Raad van Toezicht Stichting Welzijn Ridderkerk", "time": "00:22:31"}, {"agendaPoint": "11.Mededelingen college ontwikkelingen drie decentralisaties", "time": "00:00:15"}, {"agendaPoint": "13.Mededelingen college", "time": "00:02:26"}, {"agendaPoint": "14.Rondvraag leden", "time": "00:00:05"}, {"agendaPoint": "15.Ter kennisneming: overige stukken", "time": "00:00:07"}, {"agendaPoint": "16.Ter kennisneming: raadsinformatiebrieven", "time": "00:00:25"}]